sailboat_gym/__init__.py
sailboat_gym/abstracts.py
sailboat_gym/types.py
sailboat_gym/utils.py
sailboat_gym/envs/__init__.py
sailboat_gym/envs/env.py
sailboat_gym/envs/sailboat_lsa/__init__.py
sailboat_gym/envs/sailboat_lsa/lsa_env.py
sailboat_gym/envs/sailboat_lsa/lsa_sim.py
sailboat_gym/helpers/__init__.py
sailboat_gym/helpers/get_best_sail.py
sailboat_gym/helpers/get_vmc.py
sailboat_gym/pkl/SailboatLSAEnv-v0_bounds_v_wind_1.pkl
sailboat_gym/pkl/SailboatLSAEnv-v0_bounds_v_wind_2.pkl
sailboat_gym/renderers/__init__.py
sailboat_gym/renderers/cv_2d_renderer.py
tests/__init__.py
tests/check_all.py
tests/check_env.py
sailboat_gym-1.2.0.dist-info/LICENSE
sailboat_gym-1.2.0.dist-info/METADATA
sailboat_gym-1.2.0.dist-info/WHEEL
sailboat_gym-1.2.0.dist-info/top_level.txt
sailboat_gym-1.2.0.dist-info/RECORD
