Metadata-Version: 2.1
Name: sailboat-gym
Version: 1.2.0
Summary: A dynamic gym simulation environment specifically designed for sailboats.
Home-page: https://github.com/lucasmrdt/sailboat-gym
Author: Lucas Marandat
Author-email: lucas.mrdt+sailboat@gmail.com
License: MIT License
Project-URL: Homepage, https://github.com/lucasmrdt/sailboat-gym
Project-URL: Repository, https://github.com/lucasmrdt/sailboat-gym
Project-URL: Documentation, https://github.com/lucasmrdt/sailboat-gym/blob/main/DOCUMENTATION.md
Project-URL: Bug Report, https://github.com/lucasmrdt/sailboat-gym/issues
Keywords: Simulation,Sailboat,Gymnasium,Gym
Classifier: Development Status :: 4 - Beta
Classifier: License :: OSI Approved :: MIT License
Classifier: Programming Language :: Python :: 3
Classifier: Programming Language :: Python :: 3.7
Classifier: Programming Language :: Python :: 3.8
Classifier: Programming Language :: Python :: 3.9
Classifier: Programming Language :: Python :: 3.10
Classifier: Intended Audience :: Science/Research
Classifier: Topic :: Scientific/Engineering :: Artificial Intelligence
Requires-Python: >=3.7
License-File: LICENSE
Requires-Dist: gymnasium ==0.28.1
Requires-Dist: msgpack-python ==0.5.6
Requires-Dist: pyzmq ==25.0.2
Requires-Dist: numpy
Requires-Dist: pydantic
Requires-Dist: tqdm
Requires-Dist: opencv-python
Requires-Dist: imageio-ffmpeg
Requires-Dist: docker
Requires-Dist: moviepy
Requires-Dist: multiexit
